odoo10_addon_l10n_it_website_portal_fatturapa-10.0.1.0.2-nspkg.pth
odoo/addons/l10n_it_website_portal_fatturapa/README.rst
odoo/addons/l10n_it_website_portal_fatturapa/__init__.py
odoo/addons/l10n_it_website_portal_fatturapa/__manifest__.py
odoo/addons/l10n_it_website_portal_fatturapa/controllers/__init__.py
odoo/addons/l10n_it_website_portal_fatturapa/controllers/main.py
odoo/addons/l10n_it_website_portal_fatturapa/i18n/l10n_it_website_portal_fatturapa.pot
odoo/addons/l10n_it_website_portal_fatturapa/readme/DESCRIPTION.rst
odoo/addons/l10n_it_website_portal_fatturapa/readme/ROADMAP.rst
odoo/addons/l10n_it_website_portal_fatturapa/static/description/icon.png
odoo/addons/l10n_it_website_portal_fatturapa/static/description/index.html
odoo/addons/l10n_it_website_portal_fatturapa/static/src/js/l10n_it_website_portal_fatturapa.js
odoo/addons/l10n_it_website_portal_fatturapa/views/l10n_it_website_portal_fatturapa_templates.xml
odoo10_addon_l10n_it_website_portal_fatturapa-10.0.1.0.2.dist-info/METADATA
odoo10_addon_l10n_it_website_portal_fatturapa-10.0.1.0.2.dist-info/WHEEL
odoo10_addon_l10n_it_website_portal_fatturapa-10.0.1.0.2.dist-info/namespace_packages.txt
odoo10_addon_l10n_it_website_portal_fatturapa-10.0.1.0.2.dist-info/top_level.txt
odoo10_addon_l10n_it_website_portal_fatturapa-10.0.1.0.2.dist-info/RECORD
